<annotation>
    <folder>JPEGImages</folder>
    <filename>cjty4ccj3ptgm0878smvgkfyf.jpeg</filename>
    <path>C:\Users\Fredrik\OneDrive - NTNU\NTNU 8. sem\DataSyn\TDT4265-project\dataset_generator\original_dataset\JPEGImages\cjty4ccj3ptgm0878smvgkfyf.jpeg</path>
    <source>
        <database>Unknown</database>
    </source>
    <size>
        <width>1600</width>
        <height>1200</height>
        <depth>3</depth>
    </size>
    <segmented>0</segmented>
    <object>
        <name>Smoke</name>
        <pose>Unspecified</pose>
        <truncated>0</truncated>
        <difficult>0</difficult>
        <bndbox>
                <xmin>654</xmin>
                <ymin>128</ymin>
                <xmax>1018</xmax>
                <ymax>717</ymax>
            </bndbox>
        </object>
    </annotation>
